[
  {
    "info": {
      "symbol": "BTCUSDT",
      "positionAmt": "0.002",
      "entryPrice": "29125.4",
      "markPrice": "29134.66465751",
      "unRealizedProfit": "0.01852931",
      "liquidationPrice": "26329.72907631",
      "leverage": "10",
      "maxNotionalValue": "40000000",
      "marginType": "isolated",
      "isolatedMargin": "5.82050899",
      "isAutoAddMargin": "false",
      "positionSide": "LONG",
      "notional": "58.26932931",
      "isolatedWallet": "5.80197968",
      "updateTime": "1690266968109"
    },
    "id": null,
    "symbol": "BTC/USDT:USDT",
    "contracts": 0.002,
    "contractSize": 1.0,
    "unrealizedPnl": 0.01852931,
    "leverage": 10.0,
    "liquidationPrice": 26329.72907631,
    "collateral": 5.82050899,
    "notional": 58.26932931,
    "markPrice": 29134.66465751,
    "entryPrice": 29125.4,
    "timestamp": 1690266968109,
    "initialMargin": 5.82693293,
    "initialMarginPercentage": 0.1,
    "maintenanceMargin": 0.23307731724,
    "maintenanceMarginPercentage": 0.004,
    "marginRatio": 0.04,
    "datetime": "2023-07-25T06:36:08.109Z",
    "marginMode": "isolated",
    "marginType": "isolated",
    "side": "long",
    "hedged": true,
    "percentage": 0.31
  },
  {
    "info": {
      "symbol": "BTCUSDT",
      "positionAmt": "-0.002",
      "entryPrice": "29139.0",
      "markPrice": "29134.66465751",
      "unRealizedProfit": "0.00867068",
      "liquidationPrice": "31914.28725100",
      "leverage": "10",
      "maxNotionalValue": "40000000",
      "marginType": "isolated",
      "isolatedMargin": "5.81455948",
      "isAutoAddMargin": "false",
      "positionSide": "SHORT",
      "notional": "-58.26932931",
      "isolatedWallet": "5.80588880",
      "updateTime": "1690268971118"
    },
    "id": null,
    "symbol": "BTC/USDT:USDT",
    "contracts": 0.002,
    "contractSize": 1.0,
    "unrealizedPnl": 0.00867068,
    "leverage": 10.0,
    "liquidationPrice": 31914.287251,
    "collateral": 5.81455948,
    "notional": 58.26932931,
    "markPrice": 29134.66465751,
    "entryPrice": 29139.0,
    "timestamp": 1690268971118,
    "initialMargin": 5.82693293,
    "initialMarginPercentage": 0.1,
    "maintenanceMargin": 0.23307731724,
    "maintenanceMarginPercentage": 0.004,
    "marginRatio": 0.0401,
    "datetime": "2023-07-25T07:09:31.118Z",
    "marginMode": "isolated",
    "marginType": "isolated",
    "side": "short",
    "hedged": true,
    "percentage": 0.14
  }
]
